[
  {
    "date": "2025-10-03T14:42:06+0200",
    "remainingDate": "2025-10-04T03:00:00+0200",
    "preis": 270000,
    "playerName": "Heintz",
    "verein": "13",
    "wert": 260000,
    "remainingSeconds": 44273,
    "setOnMarket": "2025-10-01T04:37:33+0200",
    "position": "ABWEHR",
    "playerID": "31882",
    "status": "AKTIV"
  },
  {
    "date": "2025-10-03T14:42:06+0200",
    "remainingDate": "2025-10-06T03:00:00+0200",
    "preis": 160000,
    "playerName": "Lomb",
    "verein": "8",
    "wert": 160000,
    "remainingSeconds": 217073,
    "setOnMarket": "2025-10-03T04:24:54+0200",
    "position": "TORHÜTER",
    "playerID": "32007",
    "status": "AKTIV"
  },
  {
    "date": "2025-10-03T14:42:06+0200",
    "remainingDate": "2025-10-05T03:00:00+0200",
    "preis": 2590000,
    "playerName": "M. Wolf",
    "verein": "68",
    "wert": 2690000,
    "remainingSeconds": 130673,
    "setOnMarket": "2025-10-02T04:35:51+0200",
    "position": "ABWEHR",
    "playerID": "32546",
    "status": "AKTIV"
  },
  {
    "date": "2025-10-03T14:42:06+0200",
    "remainingDate": "2025-10-05T03:00:00+0200",
    "preis": 220000,
    "playerName": "Urbig",
    "verein": "1",
    "wert": 220000,
    "remainingSeconds": 130673,
    "setOnMarket": "2025-10-02T04:35:51+0200",
    "position": "TORHÜTER",
    "playerID": "33494",
    "status": "VERLETZT"
  },
  {
    "date": "2025-10-03T14:42:06+0200",
    "remainingDate": "2025-10-06T03:00:00+0200",
    "preis": 160000,
    "playerName": "Ostrzinski",
    "verein": "5",
    "wert": 160000,
    "remainingSeconds": 217073,
    "setOnMarket": "2025-10-03T04:36:57+0200",
    "position": "TORHÜTER",
    "playerID": "33539",
    "status": "AKTIV"
  },
  {
    "date": "2025-10-03T14:42:06+0200",
    "remainingDate": "2025-10-04T03:00:00+0200",
    "preis": 210000,
    "playerName": "Fraulo",
    "verein": "3",
    "wert": 220000,
    "remainingSeconds": 44273,
    "setOnMarket": "2025-10-01T04:25:10+0200",
    "position": "MITTELFELD",
    "playerID": "33636",
    "status": "AKTIV"
  },
  {
    "date": "2025-10-03T14:42:06+0200",
    "remainingDate": "2025-10-06T03:00:00+0200",
    "preis": 1210000,
    "playerName": "Rosenfelder",
    "verein": "21",
    "wert": 1210000,
    "remainingSeconds": 217073,
    "setOnMarket": "2025-10-03T04:36:57+0200",
    "position": "ABWEHR",
    "playerID": "33815",
    "status": "AKTIV"
  },
  {
    "date": "2025-10-03T14:42:06+0200",
    "remainingDate": "2025-10-04T03:00:00+0200",
    "preis": 170000,
    "playerName": "Kolke",
    "verein": "6",
    "wert": 160000,
    "remainingSeconds": 44273,
    "setOnMarket": "2025-10-01T04:25:10+0200",
    "position": "TORHÜTER",
    "playerID": "33986",
    "status": "AKTIV"
  },
  {
    "date": "2025-10-03T14:42:06+0200",
    "remainingDate": "2025-10-05T03:00:00+0200",
    "preis": 4550000,
    "playerName": "Ouédraogo",
    "verein": "92",
    "wert": 4660000,
    "remainingSeconds": 130673,
    "setOnMarket": "2025-10-03T01:07:07+0200",
    "position": "MITTELFELD",
    "playerID": "33991",
    "status": "AKTIV"
  },
  {
    "date": "2025-10-03T14:42:06+0200",
    "remainingDate": "2025-10-05T03:00:00+0200",
    "preis": 4570000,
    "playerName": "Essende",
    "verein": "68",
    "wert": 3790000,
    "remainingSeconds": 130673,
    "setOnMarket": "2025-10-02T07:11:00+0200",
    "position": "STURM",
    "playerID": "34005",
    "status": "ROTE_KARTE"
  },
  {
    "date": "2025-10-03T14:42:06+0200",
    "remainingDate": "2025-10-06T03:00:00+0200",
    "preis": 1600000,
    "playerName": "Chaves",
    "verein": "62",
    "wert": 1600000,
    "remainingSeconds": 217073,
    "setOnMarket": "2025-10-03T04:36:57+0200",
    "position": "ABWEHR",
    "playerID": "34062",
    "status": "AKTIV"
  },
  {
    "date": "2025-10-03T14:42:06+0200",
    "remainingDate": "2025-10-05T03:00:00+0200",
    "preis": 2650000,
    "playerName": "Nordin",
    "verein": "18",
    "wert": 2670000,
    "remainingSeconds": 130673,
    "setOnMarket": "2025-10-02T04:35:51+0200",
    "position": "MITTELFELD",
    "playerID": "34098",
    "status": "AKTIV"
  },
  {
    "date": "2025-10-03T14:42:06+0200",
    "remainingDate": "2025-10-05T03:00:00+0200",
    "preis": 4570000,
    "playerName": "Banzuzi",
    "verein": "92",
    "wert": 4460000,
    "remainingSeconds": 130673,
    "setOnMarket": "2025-10-03T01:07:58+0200",
    "position": "MITTELFELD",
    "playerID": "34185",
    "status": "AKTIV"
  },
  {
    "date": "2025-10-03T14:42:06+0200",
    "remainingDate": "2025-10-06T03:00:00+0200",
    "preis": 3990000,
    "playerName": "Philippe",
    "verein": "4",
    "wert": 3990000,
    "remainingSeconds": 217073,
    "setOnMarket": "2025-10-03T04:24:54+0200",
    "position": "STURM",
    "playerID": "34216",
    "status": "AKTIV"
  },
  {
    "date": "2025-10-03T14:42:06+0200",
    "remainingDate": "2025-10-04T03:00:00+0200",
    "preis": 5740000,
    "playerName": "Fernández",
    "verein": "8",
    "wert": 5700000,
    "remainingSeconds": 44273,
    "setOnMarket": "2025-10-01T04:37:33+0200",
    "position": "MITTELFELD",
    "playerID": "34289",
    "status": "AKTIV"
  },
  {
    "date": "2025-10-03T14:42:06+0200",
    "remainingDate": "2025-10-05T03:00:00+0200",
    "preis": 4830000,
    "playerName": "Puertas",
    "verein": "6",
    "wert": 4760000,
    "remainingSeconds": 130673,
    "setOnMarket": "2025-10-02T04:35:51+0200",
    "position": "MITTELFELD",
    "playerID": "34298",
    "status": "AKTIV"
  }
]