[
  {
    "date": "2026-03-12T05:15:12+0100",
    "punkte": 42,
    "remainingDate": "2026-03-14T03:00:00+0100",
    "preis": 2720000,
    "playerName": "Blaswich",
    "verein": "8",
    "wert": 2410000,
    "remainingSeconds": 164687,
    "setOnMarket": "2026-03-11T06:48:12+0100",
    "position": "TORHÜTER",
    "playerID": "31827",
    "status": "AKTIV"
  },
  {
    "date": "2026-03-12T05:15:12+0100",
    "punkte": 39,
    "remainingDate": "2026-03-14T03:00:00+0100",
    "preis": 1810000,
    "playerName": "Gerhardt",
    "verein": "12",
    "wert": 1720000,
    "remainingSeconds": 164687,
    "setOnMarket": "2026-03-11T04:37:32+0100",
    "position": "MITTELFELD",
    "playerID": "32280",
    "status": "AKTIV"
  },
  {
    "date": "2026-03-12T05:15:12+0100",
    "punkte": 23,
    "remainingDate": "2026-03-14T03:00:00+0100",
    "preis": 700000,
    "playerName": "Gimber",
    "verein": "110",
    "wert": 680000,
    "remainingSeconds": 164687,
    "setOnMarket": "2026-03-11T09:31:03+0100",
    "position": "ABWEHR",
    "playerID": "32457",
    "status": "AKTIV"
  },
  {
    "date": "2026-03-12T05:15:12+0100",
    "punkte": 77,
    "remainingDate": "2026-03-14T03:00:00+0100",
    "preis": 440000,
    "playerName": "Gulácsi",
    "verein": "92",
    "wert": 470000,
    "remainingSeconds": 164687,
    "setOnMarket": "2026-03-11T09:31:10+0100",
    "position": "TORHÜTER",
    "playerID": "32575",
    "status": "VERLETZT"
  },
  {
    "date": "2026-03-12T05:15:12+0100",
    "punkte": 37,
    "remainingDate": "2026-03-13T03:00:00+0100",
    "preis": 1880000,
    "playerName": "Poulsen",
    "verein": "4",
    "wert": 1760000,
    "remainingSeconds": 78287,
    "setOnMarket": "2026-03-10T04:38:25+0100",
    "position": "STURM",
    "playerID": "32591",
    "status": "AKTIV"
  },
  {
    "date": "2026-03-12T05:15:12+0100",
    "punkte": 56,
    "remainingDate": "2026-03-13T03:00:00+0100",
    "preis": 1540000,
    "playerName": "Rexhbeçaj",
    "verein": "68",
    "wert": 1410000,
    "remainingSeconds": 78287,
    "setOnMarket": "2026-03-10T23:02:25+0100",
    "position": "MITTELFELD",
    "playerID": "32817",
    "status": "AKTIV"
  },
  {
    "date": "2026-03-12T05:15:12+0100",
    "punkte": 79,
    "remainingDate": "2026-03-15T03:00:00+0100",
    "preis": 3380000,
    "playerName": "Nartey",
    "verein": "14",
    "wert": 3380000,
    "remainingSeconds": 251087,
    "setOnMarket": "2026-03-12T04:39:14+0100",
    "position": "MITTELFELD",
    "playerID": "32830",
    "status": "AKTIV"
  },
  {
    "date": "2026-03-12T05:15:12+0100",
    "punkte": 82,
    "remainingDate": "2026-03-13T03:00:00+0100",
    "preis": 6000000,
    "playerName": "K. Schlotterbeck",
    "verein": "68",
    "wert": 5000000,
    "remainingSeconds": 78287,
    "setOnMarket": "2026-03-10T21:50:41+0100",
    "position": "ABWEHR",
    "playerID": "32953",
    "status": "AKTIV"
  },
  {
    "date": "2026-03-12T05:15:12+0100",
    "punkte": 73,
    "remainingDate": "2026-03-13T03:00:00+0100",
    "preis": 2870000,
    "playerName": "Schlager",
    "verein": "92",
    "wert": 2630000,
    "remainingSeconds": 78287,
    "setOnMarket": "2026-03-10T22:32:08+0100",
    "position": "MITTELFELD",
    "playerID": "33133",
    "status": "VERLETZT"
  },
  {
    "date": "2026-03-12T05:15:12+0100",
    "punkte": 62,
    "remainingDate": "2026-03-14T03:00:00+0100",
    "preis": 1140000,
    "playerName": "Thielmann",
    "verein": "13",
    "wert": 1140000,
    "remainingSeconds": 164687,
    "setOnMarket": "2026-03-11T09:29:20+0100",
    "position": "STURM",
    "playerID": "33185",
    "status": "VERLETZT"
  },
  {
    "date": "2026-03-12T05:15:12+0100",
    "punkte": 64,
    "remainingDate": "2026-03-13T03:00:00+0100",
    "preis": 2000000,
    "playerName": "Scally",
    "verein": "3",
    "wert": 1700000,
    "remainingSeconds": 0,
    "setOnMarket": "2026-03-09T06:35:51+0100",
    "position": "ABWEHR",
    "playerID": "33258",
    "status": "AKTIV"
  },
  {
    "date": "2026-03-12T05:15:12+0100",
    "punkte": 72,
    "remainingDate": "2026-03-13T03:00:00+0100",
    "preis": 3330000,
    "playerName": "Pejčinović",
    "verein": "12",
    "wert": 3470000,
    "remainingSeconds": 78287,
    "setOnMarket": "2026-03-10T04:38:25+0100",
    "position": "STURM",
    "playerID": "33657",
    "status": "AKTIV"
  },
  {
    "date": "2026-03-12T05:15:12+0100",
    "punkte": 31,
    "remainingDate": "2026-03-14T03:00:00+0100",
    "preis": 450000,
    "playerName": "Damar",
    "verein": "62",
    "wert": 490000,
    "remainingSeconds": 164687,
    "setOnMarket": "2026-03-11T09:31:31+0100",
    "position": "MITTELFELD",
    "playerID": "33673",
    "status": "AKTIV"
  },
  {
    "date": "2026-03-12T05:15:12+0100",
    "punkte": 33,
    "remainingDate": "2026-03-15T03:00:00+0100",
    "preis": 4290000,
    "playerName": "Milošević ",
    "verein": "6",
    "wert": 4290000,
    "remainingSeconds": 251087,
    "setOnMarket": "2026-03-12T04:39:14+0100",
    "position": "STURM",
    "playerID": "33812",
    "status": "NICHT_IN_LIGA"
  },
  {
    "date": "2026-03-12T05:15:12+0100",
    "punkte": 63,
    "remainingDate": "2026-03-13T03:00:00+0100",
    "preis": 1700000,
    "playerName": "Kemlein",
    "verein": "109",
    "wert": 1650000,
    "remainingSeconds": 78287,
    "setOnMarket": "2026-03-10T23:03:07+0100",
    "position": "MITTELFELD",
    "playerID": "33821",
    "status": "AKTIV"
  },
  {
    "date": "2026-03-12T05:15:12+0100",
    "punkte": 0,
    "remainingDate": "2026-03-14T03:00:00+0100",
    "preis": 410000,
    "playerName": "Eduardo",
    "verein": "62",
    "wert": 390000,
    "remainingSeconds": 164687,
    "setOnMarket": "2026-03-11T04:37:32+0100",
    "position": "STURM",
    "playerID": "33889",
    "status": "NICHT_IN_LIGA"
  },
  {
    "date": "2026-03-12T05:15:12+0100",
    "punkte": 0,
    "remainingDate": "2026-03-15T03:00:00+0100",
    "preis": 160000,
    "playerName": "Petersson",
    "verein": "62",
    "wert": 160000,
    "remainingSeconds": 251087,
    "setOnMarket": "2026-03-12T04:26:32+0100",
    "position": "TORHÜTER",
    "playerID": "33913",
    "status": "AKTIV"
  },
  {
    "date": "2026-03-12T05:15:12+0100",
    "punkte": 68,
    "remainingDate": "2026-03-13T03:00:00+0100",
    "preis": 1540000,
    "playerName": "Niehues",
    "verein": "110",
    "wert": 1540000,
    "remainingSeconds": 78287,
    "setOnMarket": "2026-03-10T22:32:02+0100",
    "position": "MITTELFELD",
    "playerID": "33924",
    "status": "AKTIV"
  },
  {
    "date": "2026-03-12T05:15:12+0100",
    "punkte": 91,
    "remainingDate": "2026-03-14T03:00:00+0100",
    "preis": 4880000,
    "playerName": "Remberg",
    "verein": "4",
    "wert": 5020000,
    "remainingSeconds": 164687,
    "setOnMarket": "2026-03-11T09:32:19+0100",
    "position": "MITTELFELD",
    "playerID": "33935",
    "status": "AKTIV"
  },
  {
    "date": "2026-03-12T05:15:12+0100",
    "punkte": 77,
    "remainingDate": "2026-03-13T03:00:00+0100",
    "preis": 4000000,
    "playerName": "Prass",
    "verein": "62",
    "wert": 3790000,
    "remainingSeconds": 78287,
    "setOnMarket": "2026-03-10T23:02:56+0100",
    "position": "ABWEHR",
    "playerID": "34034",
    "status": "AKTIV"
  },
  {
    "date": "2026-03-12T05:15:12+0100",
    "punkte": 30,
    "remainingDate": "2026-03-14T03:00:00+0100",
    "preis": 1330000,
    "playerName": "Jaquez",
    "verein": "14",
    "wert": 1340000,
    "remainingSeconds": 164687,
    "setOnMarket": "2026-03-11T04:25:51+0100",
    "position": "ABWEHR",
    "playerID": "34112",
    "status": "AKTIV"
  },
  {
    "date": "2026-03-12T05:15:12+0100",
    "punkte": 23,
    "remainingDate": "2026-03-13T03:00:00+0100",
    "preis": 440000,
    "playerName": "Schmied",
    "verein": "13",
    "wert": 400000,
    "remainingSeconds": 78287,
    "setOnMarket": "2026-03-10T04:38:25+0100",
    "position": "ABWEHR",
    "playerID": "34135",
    "status": "VERLETZT"
  },
  {
    "date": "2026-03-12T05:15:12+0100",
    "punkte": 48,
    "remainingDate": "2026-03-13T03:00:00+0100",
    "preis": 1350000,
    "playerName": "Banzuzi",
    "verein": "92",
    "wert": 1520000,
    "remainingSeconds": 78287,
    "setOnMarket": "2026-03-10T23:06:23+0100",
    "position": "MITTELFELD",
    "playerID": "34185",
    "status": "AKTIV"
  },
  {
    "date": "2026-03-12T05:15:12+0100",
    "punkte": 76,
    "remainingDate": "2026-03-13T03:00:00+0100",
    "preis": 1970000,
    "playerName": "Ansah",
    "verein": "109",
    "wert": 2080000,
    "remainingSeconds": 78287,
    "setOnMarket": "2026-03-10T23:06:31+0100",
    "position": "STURM",
    "playerID": "34199",
    "status": "AKTIV"
  },
  {
    "date": "2026-03-12T05:15:12+0100",
    "punkte": 0,
    "remainingDate": "2026-03-13T03:00:00+0100",
    "preis": 170000,
    "playerName": "İnanoğlu",
    "verein": "0",
    "wert": 170000,
    "remainingSeconds": 78287,
    "setOnMarket": "2026-03-10T23:06:37+0100",
    "position": "STURM",
    "playerID": "34223",
    "status": "NICHT_IN_LIGA"
  },
  {
    "date": "2026-03-12T05:15:12+0100",
    "punkte": 9,
    "remainingDate": "2026-03-14T03:00:00+0100",
    "preis": 260000,
    "playerName": "Kawasaki",
    "verein": "18",
    "wert": 260000,
    "remainingSeconds": 164687,
    "setOnMarket": "2026-03-11T09:31:26+0100",
    "position": "MITTELFELD",
    "playerID": "34231",
    "status": "AKTIV"
  },
  {
    "date": "2026-03-12T05:15:12+0100",
    "punkte": 21,
    "remainingDate": "2026-03-13T03:00:00+0100",
    "preis": 1860000,
    "playerName": "Andō ",
    "verein": "25",
    "wert": 1780000,
    "remainingSeconds": 78287,
    "setOnMarket": "2026-03-10T22:32:15+0100",
    "position": "ABWEHR",
    "playerID": "34317",
    "status": "AKTIV"
  },
  {
    "date": "2026-03-12T05:15:12+0100",
    "punkte": 42,
    "remainingDate": "2026-03-14T03:00:00+0100",
    "preis": 11900000,
    "playerName": "Kalimuendo",
    "verein": "9",
    "wert": 12150000,
    "remainingSeconds": 164687,
    "setOnMarket": "2026-03-11T04:37:32+0100",
    "position": "STURM",
    "playerID": "34324",
    "status": "AKTIV"
  },
  {
    "date": "2026-03-12T05:15:12+0100",
    "punkte": 8,
    "remainingDate": "2026-03-15T03:00:00+0100",
    "preis": 980000,
    "playerName": "Chávez",
    "verein": "13",
    "wert": 980000,
    "remainingSeconds": 251087,
    "setOnMarket": "2026-03-12T04:39:14+0100",
    "position": "MITTELFELD",
    "playerID": "34328",
    "status": "AKTIV"
  },
  {
    "date": "2026-03-12T05:15:12+0100",
    "punkte": 0,
    "remainingDate": "2026-03-13T03:00:00+0100",
    "preis": 180000,
    "playerName": "Fields",
    "verein": "62",
    "wert": 190000,
    "remainingSeconds": 78287,
    "setOnMarket": "2026-03-10T04:38:25+0100",
    "position": "STURM",
    "playerID": "34336",
    "status": "AKTIV"
  },
  {
    "date": "2026-03-12T05:15:12+0100",
    "punkte": 4,
    "remainingDate": "2026-03-13T03:00:00+0100",
    "preis": 1580000,
    "playerName": "Reggiani",
    "verein": "5",
    "wert": 1420000,
    "remainingSeconds": 78287,
    "setOnMarket": "2026-03-10T04:38:25+0100",
    "position": "ABWEHR",
    "playerID": "34346",
    "status": "AKTIV"
  }
]