[
  {
    "date": "2026-03-21T15:00:44+0100",
    "punkte": 48,
    "remainingDate": "2026-03-23T03:00:00+0100",
    "preis": 2070000,
    "playerName": "Blaswich",
    "verein": "8",
    "wert": 2210000,
    "remainingSeconds": 129555,
    "setOnMarket": "2026-03-20T04:40:04+0100",
    "position": "TORHÜTER",
    "playerID": "31827",
    "status": "AKTIV"
  },
  {
    "date": "2026-03-21T15:00:44+0100",
    "punkte": 64,
    "remainingDate": "2026-03-22T03:00:00+0100",
    "preis": 1080000,
    "playerName": "Waldschmidt",
    "verein": "13",
    "wert": 1100000,
    "remainingSeconds": 43155,
    "setOnMarket": "2026-03-19T04:37:07+0100",
    "position": "STURM",
    "playerID": "32206",
    "status": "AKTIV"
  },
  {
    "date": "2026-03-21T15:00:44+0100",
    "punkte": 48,
    "remainingDate": "2026-03-24T03:00:00+0100",
    "preis": 2880000,
    "playerName": "Tietz",
    "verein": "18",
    "wert": 2880000,
    "remainingSeconds": 215955,
    "setOnMarket": "2026-03-21T04:37:18+0100",
    "position": "STURM",
    "playerID": "33070",
    "status": "AKTIV"
  },
  {
    "date": "2026-03-21T15:00:44+0100",
    "punkte": 0,
    "remainingDate": "2026-03-22T03:00:00+0100",
    "preis": 160000,
    "playerName": "Kyereh",
    "verein": "21",
    "wert": 160000,
    "remainingSeconds": 43155,
    "setOnMarket": "2026-03-19T04:37:07+0100",
    "position": "MITTELFELD",
    "playerID": "33637",
    "status": "VERLETZT"
  },
  {
    "date": "2026-03-21T15:00:44+0100",
    "punkte": 45,
    "remainingDate": "2026-03-23T03:00:00+0100",
    "preis": 710000,
    "playerName": "Honsak",
    "verein": "110",
    "wert": 680000,
    "remainingSeconds": 129555,
    "setOnMarket": "2026-03-20T04:40:04+0100",
    "position": "STURM",
    "playerID": "33797",
    "status": "AKTIV"
  },
  {
    "date": "2026-03-21T15:00:44+0100",
    "punkte": 12,
    "remainingDate": "2026-03-24T03:00:00+0100",
    "preis": 510000,
    "playerName": "Finkgräfe",
    "verein": "92",
    "wert": 510000,
    "remainingSeconds": 215955,
    "setOnMarket": "2026-03-21T04:25:34+0100",
    "position": "ABWEHR",
    "playerID": "33848",
    "status": "AKTIV"
  },
  {
    "date": "2026-03-21T15:00:44+0100",
    "punkte": 33,
    "remainingDate": "2026-03-22T03:00:00+0100",
    "preis": 1720000,
    "playerName": "Tella",
    "verein": "8",
    "wert": 2080000,
    "remainingSeconds": 43155,
    "setOnMarket": "2026-03-19T04:26:29+0100",
    "position": "MITTELFELD",
    "playerID": "33853",
    "status": "AKTIV"
  },
  {
    "date": "2026-03-21T15:00:44+0100",
    "punkte": 0,
    "remainingDate": "2026-03-23T03:00:00+0100",
    "preis": 160000,
    "playerName": "Klaus",
    "verein": "109",
    "wert": 160000,
    "remainingSeconds": 129555,
    "setOnMarket": "2026-03-20T04:26:39+0100",
    "position": "TORHÜTER",
    "playerID": "34032",
    "status": "AKTIV"
  },
  {
    "date": "2026-03-21T15:00:44+0100",
    "punkte": 53,
    "remainingDate": "2026-03-24T03:00:00+0100",
    "preis": 1910000,
    "playerName": "Jeltsch",
    "verein": "14",
    "wert": 1910000,
    "remainingSeconds": 215955,
    "setOnMarket": "2026-03-21T04:37:18+0100",
    "position": "ABWEHR",
    "playerID": "34115",
    "status": "AKTIV"
  },
  {
    "date": "2026-03-21T15:00:44+0100",
    "punkte": 97,
    "remainingDate": "2026-03-23T03:00:00+0100",
    "preis": 6000000,
    "playerName": "Avdullahu",
    "verein": "62",
    "wert": 5270000,
    "remainingSeconds": 129555,
    "setOnMarket": "2026-03-20T14:17:58+0100",
    "position": "MITTELFELD",
    "playerID": "34202",
    "status": "VERLETZT"
  },
  {
    "date": "2026-03-21T15:00:44+0100",
    "punkte": 171,
    "remainingDate": "2026-03-22T03:00:00+0100",
    "preis": 21230000,
    "playerName": "Diomande",
    "verein": "92",
    "wert": 21120000,
    "remainingSeconds": 43155,
    "setOnMarket": "2026-03-19T04:37:07+0100",
    "position": "STURM",
    "playerID": "34237",
    "status": "AKTIV"
  },
  {
    "date": "2026-03-21T15:00:44+0100",
    "punkte": 0,
    "remainingDate": "2026-03-24T03:00:00+0100",
    "preis": 160000,
    "playerName": "Tangvik",
    "verein": "4",
    "wert": 160000,
    "remainingSeconds": 215955,
    "setOnMarket": "2026-03-21T04:37:18+0100",
    "position": "TORHÜTER",
    "playerID": "34334",
    "status": "AKTIV"
  },
  {
    "date": "2026-03-21T15:00:44+0100",
    "punkte": 1,
    "remainingDate": "2026-03-23T03:00:00+0100",
    "preis": 1070000,
    "playerName": "Adjetey",
    "verein": "12",
    "wert": 1030000,
    "remainingSeconds": 129555,
    "setOnMarket": "2026-03-20T04:40:04+0100",
    "position": "ABWEHR",
    "playerID": "34343",
    "status": "AKTIV"
  },
  {
    "date": "2026-03-21T15:00:44+0100",
    "punkte": 2,
    "remainingDate": "2026-03-22T03:00:00+0100",
    "preis": 1040000,
    "playerName": "Cardozo",
    "verein": "1",
    "wert": 1160000,
    "remainingSeconds": 43155,
    "setOnMarket": "2026-03-19T04:37:07+0100",
    "position": "STURM",
    "playerID": "34350",
    "status": "AKTIV"
  }
]